{
  "Gold": [
    {
      "team": "gold1",
      "wins": 0,
      "totalRaces": 0,
      "points": 0,
      "winPercentage": 0,
      "place": 1,
      "league": "Gold",
      "tiebreakNote": "Tied with gold2, gold3, gold4 (all tiebreakers exhausted)"
    },
    {
      "team": "gold2",
      "wins": 0,
      "totalRaces": 0,
      "points": 0,
      "winPercentage": 0,
      "place": 1,
      "league": "Gold",
      "tiebreakNote": "Tied with gold1, gold3, gold4 (all tiebreakers exhausted)"
    },
    {
      "team": "gold3",
      "wins": 0,
      "totalRaces": 0,
      "points": 0,
      "winPercentage": 0,
      "place": 1,
      "league": "Gold",
      "tiebreakNote": "Tied with gold1, gold2, gold4 (all tiebreakers exhausted)"
    },
    {
      "team": "gold4",
      "wins": 0,
      "totalRaces": 0,
      "points": 0,
      "winPercentage": 0,
      "place": 1,
      "league": "Gold",
      "tiebreakNote": "Tied with gold1, gold2, gold3 (all tiebreakers exhausted)"
    }
  ],
  "Silver": [
    {
      "team": "silver1",
      "wins": 0,
      "totalRaces": 0,
      "points": 0,
      "winPercentage": 0,
      "place": 1,
      "league": "Silver",
      "tiebreakNote": "Tied with silver2, silver3, silver4 (all tiebreakers exhausted)"
    },
    {
      "team": "silver2",
      "wins": 0,
      "totalRaces": 0,
      "points": 0,
      "winPercentage": 0,
      "place": 1,
      "league": "Silver",
      "tiebreakNote": "Tied with silver1, silver3, silver4 (all tiebreakers exhausted)"
    },
    {
      "team": "silver3",
      "wins": 0,
      "totalRaces": 0,
      "points": 0,
      "winPercentage": 0,
      "place": 1,
      "league": "Silver",
      "tiebreakNote": "Tied with silver1, silver2, silver4 (all tiebreakers exhausted)"
    },
    {
      "team": "silver4",
      "wins": 0,
      "totalRaces": 0,
      "points": 0,
      "winPercentage": 0,
      "place": 1,
      "league": "Silver",
      "tiebreakNote": "Tied with silver1, silver2, silver3 (all tiebreakers exhausted)"
    }
  ]
}